chuck_data/__init__.py
chuck_data/__main__.py
chuck_data/api_client.py
chuck_data/catalogs.py
chuck_data/command_models.py
chuck_data/command_output.py
chuck_data/command_registry.py
chuck_data/config.py
chuck_data/constants.py
chuck_data/databricks_auth.py
chuck_data/exceptions.py
chuck_data/interactive_context.py
chuck_data/interactive_handler.py
chuck_data/job_cache.py
chuck_data/logger.py
chuck_data/metrics_collector.py
chuck_data/models.py
chuck_data/profiler.py
chuck_data/service.py
chuck_data/utils.py
chuck_data/version.py
chuck_data/warehouses.py
chuck_data/agent/__init__.py
chuck_data/agent/manager.py
chuck_data/agent/tool_executor.py
chuck_data/agent/prompts/__init__.py
chuck_data/agent/prompts/default_system_prompt.py
chuck_data/agent/prompts/pii_prompts.py
chuck_data/agent/prompts/stitch_prompts.py
chuck_data/assets/stitch_notebook_template.ipynb
chuck_data/clients/__init__.py
chuck_data/clients/amperity.py
chuck_data/clients/databricks.py
chuck_data/commands/__init__.py
chuck_data/commands/add_stitch_report.py
chuck_data/commands/agent.py
chuck_data/commands/auth.py
chuck_data/commands/base.py
chuck_data/commands/bug.py
chuck_data/commands/bulk_tag_pii.py
chuck_data/commands/catalog.py
chuck_data/commands/catalog_selection.py
chuck_data/commands/cluster_init_tools.py
chuck_data/commands/create_volume.py
chuck_data/commands/create_warehouse.py
chuck_data/commands/discord.py
chuck_data/commands/getting_started.py
chuck_data/commands/help.py
chuck_data/commands/job_status.py
chuck_data/commands/jobs.py
chuck_data/commands/list_catalogs.py
chuck_data/commands/list_models.py
chuck_data/commands/list_schemas.py
chuck_data/commands/list_tables.py
chuck_data/commands/list_volumes.py
chuck_data/commands/list_warehouses.py
chuck_data/commands/model_selection.py
chuck_data/commands/monitor_job.py
chuck_data/commands/pii_tools.py
chuck_data/commands/run_sql.py
chuck_data/commands/scan_pii.py
chuck_data/commands/schema.py
chuck_data/commands/schema_selection.py
chuck_data-0.3.0.dist-info/METADATA
chuck_data-0.3.0.dist-info/WHEEL
chuck_data-0.3.0.dist-info/entry_points.txt
chuck_data-0.3.0.dist-info/licenses/LICENSE
chuck_data-0.3.0.dist-info/RECORD
