Metadata-Version: 2.4
Name: chuck-data
Version: 0.3.0
Summary: Command line AI for customer data
Project-URL: Homepage, https://github.com/amperity/chuck-data
Project-URL: Repository, https://github.com/amperity/chuck-data
Author-email: John Rush <john.rush@amperity.com>, Caleb Benningfield <noodles@amperity.com>
License: Apache-2.0
License-File: LICENSE
Keywords: agents,ai,customer data,databricks,llm
Classifier: Intended Audience :: Developers
Classifier: Intended Audience :: Information Technology
Classifier: Intended Audience :: System Administrators
Classifier: License :: OSI Approved :: Apache Software License
Classifier: Natural Language :: English
Classifier: Operating System :: OS Independent
Classifier: Programming Language :: Python :: 3
Classifier: Topic :: Scientific/Engineering :: Artificial Intelligence
Classifier: Topic :: Software Development :: Build Tools
Requires-Python: >=3.10
Requires-Dist: boto3>=1.28.0
Requires-Dist: databricks-sdk>=0.50.0
Requires-Dist: jsonschema>=4.23.0
Requires-Dist: openai>=1.76.0
Requires-Dist: prettytable>=3.12.0
Requires-Dist: prompt-toolkit>=3.0.50
Requires-Dist: pydantic>=2.11.3
Requires-Dist: readchar>=4.2.1
Requires-Dist: requests>=2.32.3
Requires-Dist: textual>=0.40.0
Provides-Extra: dev
Requires-Dist: black; extra == 'dev'
Requires-Dist: pexpect; extra == 'dev'
Requires-Dist: pyright; extra == 'dev'
Requires-Dist: pytest; extra == 'dev'
Requires-Dist: pytest-cov; extra == 'dev'
Requires-Dist: ruff; extra == 'dev'
